team_mates/__init__.py
team_mates/__main__.py
team_mates/gitdata.py
team_mates/helpers.py
team_mates/server.py
team_mates/templates/favicon.ico
team_mates/templates/index.html
team_mates/templates/main-es2015.js
team_mates/templates/main-es2015.js.map
team_mates/templates/main-es5.js
team_mates/templates/main-es5.js.map
team_mates/templates/polyfills-es2015.js
team_mates/templates/polyfills-es2015.js.map
team_mates/templates/polyfills-es5.js
team_mates/templates/polyfills-es5.js.map
team_mates/templates/runtime-es2015.js
team_mates/templates/runtime-es2015.js.map
team_mates/templates/runtime-es5.js
team_mates/templates/runtime-es5.js.map
team_mates/templates/styles-es2015.js
team_mates/templates/styles-es2015.js.map
team_mates/templates/styles-es5.js
team_mates/templates/styles-es5.js.map
team_mates/templates/vendor-es2015.js
team_mates/templates/vendor-es2015.js.map
team_mates/templates/vendor-es5.js
team_mates/templates/vendor-es5.js.map
team_mates/templates/__pycache__/__init__.cpython-37.pyc
team_mates-0.0.5.dist-info/METADATA
team_mates-0.0.5.dist-info/WHEEL
team_mates-0.0.5.dist-info/entry_points.txt
team_mates-0.0.5.dist-info/top_level.txt
team_mates-0.0.5.dist-info/RECORD
