Metadata-Version: 2.1
Name: team-mates
Version: 0.0.5
Summary: A library to analyze team mates contributions to projects.
Home-page: https://github.com/pypa/team-mates
Author: Sylvan LE DEUNFF
Author-email: sylvan.ledeunff@gmail.com
License: UNKNOWN
Platform: UNKNOWN
Classifier: Programming Language :: Python :: 3
Classifier: License :: OSI Approved :: MIT License
Classifier: Operating System :: OS Independent
Requires-Python: >=3.6
Requires-Dist: flask
Requires-Dist: gunicorn
